akvmodel.py
akvmodel-1.2.3.dist-info/METADATA
akvmodel-1.2.3.dist-info/WHEEL
akvmodel-1.2.3.dist-info/licenses/LICENSE
akvmodel-1.2.3.dist-info/RECORD
