Metadata-Version: 2.3
Name: akvmodel
Version: 1.2.3
Summary: A tool for social network simulations in the Alvim-Knight-Valencia model.
Project-URL: Homepage, https://github.com/joseoliveirajr/akvmodel
Project-URL: Bug Tracker, https://github.com/joseoliveirajr/akvmodel/issues
Author-email: "José C. Oliveira" <josecarlosdeoliveirajr@gmail.com>, Sophia Knight <sophia.knight@gmail.com>
Maintainer-email: "José C. Oliveira" <josecarlosdeoliveirajr@gmail.com>
License: MIT License
License-File: LICENSE
Classifier: Development Status :: 5 - Production/Stable
Classifier: Intended Audience :: Science/Research
Classifier: License :: OSI Approved :: MIT License
Classifier: Operating System :: OS Independent
Classifier: Topic :: Scientific/Engineering
Requires-Python: >=3.10
Requires-Dist: matplotlib
Requires-Dist: numpy
